hadder/__init__.py
hadder/__main__.py
hadder/constants.py
hadder/parsers.py
hadder-3.8.dist-info/LICENSE
hadder-3.8.dist-info/METADATA
hadder-3.8.dist-info/WHEEL
hadder-3.8.dist-info/top_level.txt
hadder-3.8.dist-info/RECORD
