Metadata-Version: 2.1
Name: hadder
Version: 3.8
Summary: Hydrogen adder for pdb protein files
Home-page: https://gitee.com/dechin/hadder
Author: Dechin CHEN
Author-email: dechin.phy@gmail.com
License: Apache 2.0 Licence
Platform: any
License-File: LICENSE
Requires-Dist: numpy
Requires-Dist: flake8
